sequentialdw/__init__.py
sequentialdw/seq_download.py
sequentialdw-4.0.dist-info/METADATA
sequentialdw-4.0.dist-info/WHEEL
sequentialdw-4.0.dist-info/entry_points.txt
sequentialdw-4.0.dist-info/top_level.txt
sequentialdw-4.0.dist-info/RECORD
