Metadata-Version: 2.1
Name: sequentialdw
Version: 4.0
Summary: A simple website scrapper with sequential files in it.
Author: wweziza
Requires-Dist: requests
